{
  "_class": "shapeGroup",
  "clippingMaskMode": 0,
  "do_objectID": "E432346D-4915-423C-8F1B-43A8A5CBB4ED",
  "exportOptions": {
    "_class": "exportOptions",
    "exportFormats": [
    ],
    "includedLayerIds": [
    ],
    "layerOptions": 0,
    "shouldTrim": false
  },
  "frame": {
    "_class": "rect",
    "constrainProportions": true,
    "height": 96,
    "width": 96,
    "x": 0,
    "y": 0
  },
  "hasClickThrough": false,
  "hasClippingMask": false,
  "isFlippedHorizontal": false,
  "isFlippedVertical": false,
  "isLocked": false,
  "isVisible": true,
  "layerListExpandedType": 0,
  "layers": [
    {
      "class": "rectangle",
      "id": "4497278E-8397-4C47-910A-33D695C84D0D"
    }
  ],
  "name": "Box",
  "nameIsFixed": true,
  "resizingConstraint": 63,
  "resizingType": 0,
  "rotation": 0,
  "shouldBreakMaskChain": false,
  "style": {
    "_class": "style",
    "borders": [
      {
        "_class": "border",
        "color": {
          "_class": "color",
          "alpha": 1,
          "blue": 0.592,
          "green": 0.592,
          "red": 0.592
        },
        "fillType": 0,
        "isEnabled": false,
        "position": 1,
        "thickness": 1
      }
    ],
    "endDecorationType": 0,
    "fills": [
      {
        "_class": "fill",
        "color": {
          "_class": "color",
          "alpha": 1,
          "blue": 1,
          "green": 1,
          "red": 1
        },
        "fillType": 0,
        "isEnabled": true,
        "noiseIndex": 0,
        "noiseIntensity": 0,
        "patternFillType": 1,
        "patternTileScale": 1
      }
    ],
    "miterLimit": 10,
    "shadows": [
      {
        "_class": "shadow",
        "blurRadius": 10,
        "color": {
          "_class": "color",
          "alpha": 0.2993942481884058,
          "blue": 0,
          "green": 0,
          "red": 0
        },
        "contextSettings": {
          "_class": "graphicsContextSettings",
          "blendMode": 0,
          "opacity": 1
        },
        "isEnabled": false,
        "offsetX": 0,
        "offsetY": 8,
        "spread": 0
      }
    ],
    "startDecorationType": 0
  },
  "userInfo": {
    "com.animaapp.stc-sketch-plugin": {
      "kModelPropertiesKey": {
        "constraints": {
          "aspectRatio": {
            "constant": 148,
            "enabled": 1,
            "modelID": "constraint_82a55081-6f4f-4300-9a37-996f720b4f26",
            "model_class": "ADModelConstraint",
            "model_version": 0.1,
            "multiplier": 148
          },
          "automatic": 1,
          "modelID": "viewConstraints_457aa212-d748-4b58-b0dc-f440a0a94d62",
          "model_class": "ADModelViewConstraints",
          "model_version": 0.1,
          "scaleFactor": 1
        }
      }
    }
  },
  "windingRule": 1
}