{
  "_class": "shapeGroup",
  "clippingMaskMode": 0,
  "do_objectID": "DD00EB94-80E1-4911-9774-F7078DAC4654",
  "exportOptions": {
    "_class": "exportOptions",
    "do_objectID": "2CE1CD95-31F5-47F5-96A1-E061F22D5489",
    "exportFormats": [
    ],
    "includedLayerIds": [
    ],
    "layerOptions": 0,
    "shouldTrim": false
  },
  "frame": {
    "_class": "rect",
    "constrainProportions": false,
    "do_objectID": "8648C5E0-F734-43D4-B965-FA4BE3470DEE",
    "height": 22,
    "width": 22,
    "x": 0,
    "y": 0
  },
  "hasClickThrough": false,
  "hasClippingMask": false,
  "isFlippedHorizontal": false,
  "isFlippedVertical": false,
  "isLocked": false,
  "isVisible": true,
  "layerListExpandedType": 0,
  "layers": [
    {
      "class": "shapePath",
      "id": "9DA4BCCE-9C73-4B88-96AA-4E6BDC3566AF"
    }
  ],
  "name": "Bounds",
  "nameIsFixed": false,
  "resizingConstraint": 63,
  "resizingType": 0,
  "rotation": 0,
  "shouldBreakMaskChain": false,
  "style": {
    "_class": "style",
    "do_objectID": "31D71691-5AC7-4E4A-BEA2-1D041673BFF1",
    "endDecorationType": 0,
    "miterLimit": 10,
    "startDecorationType": 0
  },
  "windingRule": 1
}