{
  "_class": "shapeGroup",
  "clippingMaskMode": 0,
  "do_objectID": "2F58B764-F0FB-46BB-AE77-B62B8A205242",
  "exportOptions": {
    "_class": "exportOptions",
    "do_objectID": "E71DBCEE-654E-4256-8719-26CDF1929040",
    "exportFormats": [
    ],
    "includedLayerIds": [
    ],
    "layerOptions": 0,
    "shouldTrim": false
  },
  "frame": {
    "_class": "rect",
    "constrainProportions": false,
    "do_objectID": "95E6B79D-BFA6-42C8-9939-45DA5D195A2D",
    "height": 216,
    "width": 320,
    "x": 0,
    "y": 0
  },
  "hasClickThrough": false,
  "hasClippingMask": false,
  "isFlippedHorizontal": false,
  "isFlippedVertical": false,
  "isLocked": false,
  "isVisible": true,
  "layerListExpandedType": 0,
  "layers": [
    {
      "class": "rectangle",
      "id": "E91278DD-5D24-46EC-9B6B-0A29C369E4F1"
    }
  ],
  "name": "Background",
  "nameIsFixed": true,
  "originalObjectID": "D57B8972-87D3-4E05-9898-80F1A28DCA08",
  "resizingConstraint": 63,
  "resizingType": 0,
  "rotation": 0,
  "shouldBreakMaskChain": false,
  "style": {
    "_class": "style",
    "blur": {
      "_class": "blur",
      "center": "{0.5, 0.5}",
      "do_objectID": "3DB28A09-F7C9-4FD0-BDD8-4CE45D81F572",
      "isEnabled": false,
      "motionAngle": 0,
      "radius": 5,
      "type": 0
    },
    "borders": [
      {
        "_class": "border",
        "color": {
          "_class": "color",
          "alpha": 1,
          "blue": 0.592,
          "green": 0.592,
          "red": 0.592
        },
        "fillType": 0,
        "isEnabled": false,
        "position": 1,
        "thickness": 0.5
      }
    ],
    "do_objectID": "FA5A4B78-5627-462C-81CB-2567BF267322",
    "endDecorationType": 0,
    "fills": [
      {
        "_class": "fill",
        "color": {
          "_class": "color",
          "alpha": 1,
          "blue": 0.1058823529411765,
          "green": 0.1019607843137255,
          "red": 0.1019607843137255
        },
        "fillType": 0,
        "isEnabled": true,
        "noiseIndex": 0,
        "noiseIntensity": 0,
        "patternFillType": 0,
        "patternTileScale": 1
      }
    ],
    "miterLimit": 10,
    "startDecorationType": 0
  },
  "windingRule": 1
}