{
  "_class": "shapePath",
  "booleanOperation": -1,
  "do_objectID": "F5345595-08B9-4ACB-8607-A79D5F657388",
  "edited": true,
  "exportOptions": {
    "_class": "exportOptions",
    "do_objectID": "5122995D-65DC-4906-BB20-5630EF04830A",
    "exportFormats": [
    ],
    "includedLayerIds": [
    ],
    "layerOptions": 0,
    "shouldTrim": false
  },
  "frame": {
    "_class": "rect",
    "constrainProportions": false,
    "do_objectID": "65268CD5-9AE0-42AF-AE54-38EBDF8BB038",
    "height": 7,
    "width": 20,
    "x": 1,
    "y": 14.5
  },
  "isClosed": true,
  "isFlippedHorizontal": false,
  "isFlippedVertical": false,
  "isLocked": false,
  "isVisible": true,
  "layerListExpandedType": 0,
  "name": "Shape",
  "nameIsFixed": false,
  "path": {
    "_class": "path",
    "isClosed": true,
    "pointRadiusBehaviour": 0,
    "points": [
      {
        "_class": "curvePoint",
        "cornerRadius": 0,
        "curveFrom": "{0.32670900000000003, 0}",
        "curveMode": 1,
        "curveTo": "{0.32670900000000003, 0}",
        "hasCurveFrom": false,
        "hasCurveTo": false,
        "point": "{0.32670900000000003, 0}"
      },
      {
        "_class": "curvePoint",
        "cornerRadius": 0,
        "curveFrom": "{0, 0}",
        "curveMode": 1,
        "curveTo": "{0, 0}",
        "hasCurveFrom": false,
        "hasCurveTo": false,
        "point": "{0, 0}"
      },
      {
        "_class": "curvePoint",
        "cornerRadius": 0,
        "curveFrom": "{0, 1}",
        "curveMode": 1,
        "curveTo": "{0, 1}",
        "hasCurveFrom": false,
        "hasCurveTo": false,
        "point": "{0, 1}"
      },
      {
        "_class": "curvePoint",
        "cornerRadius": 0,
        "curveFrom": "{1, 1}",
        "curveMode": 1,
        "curveTo": "{1, 1}",
        "hasCurveFrom": false,
        "hasCurveTo": false,
        "point": "{1, 1}"
      },
      {
        "_class": "curvePoint",
        "cornerRadius": 0,
        "curveFrom": "{1, 0}",
        "curveMode": 1,
        "curveTo": "{1, 0}",
        "hasCurveFrom": false,
        "hasCurveTo": false,
        "point": "{1, 0}"
      },
      {
        "_class": "curvePoint",
        "cornerRadius": 0,
        "curveFrom": "{0.66137499999999994, 0.24222857142857127}",
        "curveMode": 4,
        "curveTo": "{0.67328999999999994, 0}",
        "hasCurveFrom": true,
        "hasCurveTo": false,
        "point": "{0.67328999999999994, 0}"
      },
      {
        "_class": "curvePoint",
        "cornerRadius": 0,
        "curveFrom": "{0.50049999999999994, 0.42857142857142855}",
        "curveMode": 4,
        "curveTo": "{0.58855999999999997, 0.42857142857142855}",
        "hasCurveFrom": false,
        "hasCurveTo": true,
        "point": "{0.50049999999999994, 0.42857142857142855}"
      },
      {
        "_class": "curvePoint",
        "cornerRadius": 0,
        "curveFrom": "{0.41143799999999997, 0.42857142857142855}",
        "curveMode": 4,
        "curveTo": "{0.4995, 0.42857142857142855}",
        "hasCurveFrom": true,
        "hasCurveTo": false,
        "point": "{0.4995, 0.42857142857142855}"
      },
      {
        "_class": "curvePoint",
        "cornerRadius": 0,
        "curveFrom": "{0.32670900000000003, 0}",
        "curveMode": 4,
        "curveTo": "{0.33862300000000001, 0.24222857142857127}",
        "hasCurveFrom": false,
        "hasCurveTo": true,
        "point": "{0.32670900000000003, 0}"
      }
    ]
  },
  "pointRadiusBehaviour": 0,
  "points": [
    {
      "_class": "curvePoint",
      "cornerRadius": 0,
      "curveFrom": "{0.32670900000000003, 0}",
      "curveMode": 1,
      "curveTo": "{0.32670900000000003, 0}",
      "hasCurveFrom": false,
      "hasCurveTo": false,
      "point": "{0.32670900000000003, 0}"
    },
    {
      "_class": "curvePoint",
      "cornerRadius": 0,
      "curveFrom": "{0, 0}",
      "curveMode": 1,
      "curveTo": "{0, 0}",
      "hasCurveFrom": false,
      "hasCurveTo": false,
      "point": "{0, 0}"
    },
    {
      "_class": "curvePoint",
      "cornerRadius": 0,
      "curveFrom": "{0, 1}",
      "curveMode": 1,
      "curveTo": "{0, 1}",
      "hasCurveFrom": false,
      "hasCurveTo": false,
      "point": "{0, 1}"
    },
    {
      "_class": "curvePoint",
      "cornerRadius": 0,
      "curveFrom": "{1, 1}",
      "curveMode": 1,
      "curveTo": "{1, 1}",
      "hasCurveFrom": false,
      "hasCurveTo": false,
      "point": "{1, 1}"
    },
    {
      "_class": "curvePoint",
      "cornerRadius": 0,
      "curveFrom": "{1, 0}",
      "curveMode": 1,
      "curveTo": "{1, 0}",
      "hasCurveFrom": false,
      "hasCurveTo": false,
      "point": "{1, 0}"
    },
    {
      "_class": "curvePoint",
      "cornerRadius": 0,
      "curveFrom": "{0.66137499999999994, 0.24222857142857127}",
      "curveMode": 4,
      "curveTo": "{0.67328999999999994, 0}",
      "hasCurveFrom": true,
      "hasCurveTo": false,
      "point": "{0.67328999999999994, 0}"
    },
    {
      "_class": "curvePoint",
      "cornerRadius": 0,
      "curveFrom": "{0.50049999999999994, 0.42857142857142855}",
      "curveMode": 4,
      "curveTo": "{0.58855999999999997, 0.42857142857142855}",
      "hasCurveFrom": false,
      "hasCurveTo": true,
      "point": "{0.50049999999999994, 0.42857142857142855}"
    },
    {
      "_class": "curvePoint",
      "cornerRadius": 0,
      "curveFrom": "{0.41143799999999997, 0.42857142857142855}",
      "curveMode": 4,
      "curveTo": "{0.4995, 0.42857142857142855}",
      "hasCurveFrom": true,
      "hasCurveTo": false,
      "point": "{0.4995, 0.42857142857142855}"
    },
    {
      "_class": "curvePoint",
      "cornerRadius": 0,
      "curveFrom": "{0.32670900000000003, 0}",
      "curveMode": 4,
      "curveTo": "{0.33862300000000001, 0.24222857142857127}",
      "hasCurveFrom": false,
      "hasCurveTo": true,
      "point": "{0.32670900000000003, 0}"
    }
  ],
  "resizingConstraint": 63,
  "resizingType": 0,
  "rotation": 0,
  "shouldBreakMaskChain": false
}