{
  "_class": "shapeGroup",
  "clippingMaskMode": 0,
  "do_objectID": "3D6AADBD-3861-47EE-B11F-E0D6823760E1",
  "exportOptions": {
    "_class": "exportOptions",
    "do_objectID": "F50E526D-D5FB-49C4-9A8A-DBA3CA8B1E45",
    "exportFormats": [
    ],
    "includedLayerIds": [
    ],
    "layerOptions": 0,
    "shouldTrim": false
  },
  "frame": {
    "_class": "rect",
    "constrainProportions": false,
    "do_objectID": "3460FDE8-9322-460F-84B1-028CB49F0099",
    "height": 42,
    "width": 46.5,
    "x": 214.5,
    "y": 108
  },
  "hasClickThrough": false,
  "hasClippingMask": false,
  "isFlippedHorizontal": false,
  "isFlippedVertical": false,
  "isLocked": false,
  "isVisible": true,
  "layerListExpandedType": 0,
  "layers": [
    {
      "class": "rectangle",
      "id": "5095DF6F-859E-4590-A31F-E467A9B64A8D"
    }
  ],
  "name": "Shape",
  "nameIsFixed": false,
  "originalObjectID": "EC9BBC47-8931-4F50-8696-AEBD7323AC6C",
  "resizingConstraint": 63,
  "resizingType": 0,
  "rotation": 0,
  "shouldBreakMaskChain": false,
  "style": {
    "_class": "style",
    "blur": {
      "_class": "blur",
      "center": "{0.5, 0.5}",
      "do_objectID": "2AA20A6B-BF19-403E-B460-8E9EC58CF15D",
      "isEnabled": false,
      "motionAngle": 0,
      "radius": 5,
      "type": 0
    },
    "borders": [
      {
        "_class": "border",
        "color": {
          "_class": "color",
          "alpha": 1,
          "blue": 0.592,
          "green": 0.592,
          "red": 0.592
        },
        "fillType": 0,
        "isEnabled": false,
        "position": 1,
        "thickness": 0.5
      }
    ],
    "do_objectID": "A3B6ADEE-CE0B-47C5-B4D7-C76136DBBA35",
    "endDecorationType": 0,
    "fills": [
      {
        "_class": "fill",
        "color": {
          "_class": "color",
          "alpha": 1,
          "blue": 0.3803921568627451,
          "green": 0.3803921568627451,
          "red": 0.3803921568627451
        },
        "fillType": 0,
        "isEnabled": true,
        "noiseIndex": 0,
        "noiseIntensity": 0,
        "patternFillType": 0,
        "patternTileScale": 1
      }
    ],
    "miterLimit": 10,
    "shadows": [
      {
        "_class": "shadow",
        "blurRadius": 0,
        "color": {
          "_class": "color",
          "alpha": 0.4,
          "blue": 0,
          "green": 0,
          "red": 0
        },
        "contextSettings": {
          "_class": "graphicsContextSettings",
          "blendMode": 0,
          "opacity": 1
        },
        "isEnabled": true,
        "offsetX": 0,
        "offsetY": 1,
        "spread": 0
      }
    ],
    "startDecorationType": 0
  },
  "windingRule": 1
}