{
  "_class": "rectangle",
  "booleanOperation": -1,
  "do_objectID": "C63B34B6-F0AE-4E39-ABC8-A9E054927BBA",
  "edited": false,
  "exportOptions": {
    "_class": "exportOptions",
    "do_objectID": "77B5B2D3-BA49-4542-BF11-433A57E5E72A",
    "exportFormats": [
    ],
    "includedLayerIds": [
    ],
    "layerOptions": 0,
    "shouldTrim": false
  },
  "fixedRadius": 0,
  "frame": {
    "_class": "rect",
    "constrainProportions": false,
    "do_objectID": "79419A57-0F4E-49E4-A31D-0A59FA025354",
    "height": 226.0000000000002,
    "width": 414,
    "x": 0,
    "y": 0
  },
  "hasConvertedToNewRoundCorners": true,
  "isClosed": true,
  "isFlippedHorizontal": false,
  "isFlippedVertical": false,
  "isLocked": false,
  "isVisible": true,
  "layerListExpandedType": 0,
  "name": "Path",
  "nameIsFixed": false,
  "path": {
    "_class": "path",
    "isClosed": true,
    "pointRadiusBehaviour": 0,
    "points": [
      {
        "_class": "curvePoint",
        "cornerRadius": 0,
        "curveFrom": "{0, 0}",
        "curveMode": 1,
        "curveTo": "{0, 0}",
        "hasCurveFrom": false,
        "hasCurveTo": false,
        "point": "{0, 0}"
      },
      {
        "_class": "curvePoint",
        "cornerRadius": 0,
        "curveFrom": "{1, 0}",
        "curveMode": 1,
        "curveTo": "{1, 0}",
        "hasCurveFrom": false,
        "hasCurveTo": false,
        "point": "{1, 0}"
      },
      {
        "_class": "curvePoint",
        "cornerRadius": 0,
        "curveFrom": "{1, 1}",
        "curveMode": 1,
        "curveTo": "{1, 1}",
        "hasCurveFrom": false,
        "hasCurveTo": false,
        "point": "{1, 1}"
      },
      {
        "_class": "curvePoint",
        "cornerRadius": 0,
        "curveFrom": "{0, 1}",
        "curveMode": 1,
        "curveTo": "{0, 1}",
        "hasCurveFrom": false,
        "hasCurveTo": false,
        "point": "{0, 1}"
      }
    ]
  },
  "pointRadiusBehaviour": 0,
  "points": [
    {
      "_class": "curvePoint",
      "cornerRadius": 0,
      "curveFrom": "{0, 0}",
      "curveMode": 1,
      "curveTo": "{0, 0}",
      "hasCurveFrom": false,
      "hasCurveTo": false,
      "point": "{0, 0}"
    },
    {
      "_class": "curvePoint",
      "cornerRadius": 0,
      "curveFrom": "{1, 0}",
      "curveMode": 1,
      "curveTo": "{1, 0}",
      "hasCurveFrom": false,
      "hasCurveTo": false,
      "point": "{1, 0}"
    },
    {
      "_class": "curvePoint",
      "cornerRadius": 0,
      "curveFrom": "{1, 1}",
      "curveMode": 1,
      "curveTo": "{1, 1}",
      "hasCurveFrom": false,
      "hasCurveTo": false,
      "point": "{1, 1}"
    },
    {
      "_class": "curvePoint",
      "cornerRadius": 0,
      "curveFrom": "{0, 1}",
      "curveMode": 1,
      "curveTo": "{0, 1}",
      "hasCurveFrom": false,
      "hasCurveTo": false,
      "point": "{0, 1}"
    }
  ],
  "resizingConstraint": 63,
  "resizingType": 0,
  "rotation": 0,
  "shouldBreakMaskChain": false
}