{
  "_class": "shapeGroup",
  "clippingMaskMode": 0,
  "do_objectID": "25533382-3112-4956-B4D4-960997AB673F",
  "exportOptions": {
    "_class": "exportOptions",
    "do_objectID": "110BBDD8-E1C9-4800-AC2E-5D45E0B56ACF",
    "exportFormats": [
    ],
    "includedLayerIds": [
    ],
    "layerOptions": 0,
    "shouldTrim": false
  },
  "frame": {
    "_class": "rect",
    "constrainProportions": false,
    "do_objectID": "F23D060F-60F2-4ADF-B71D-E12A4AB3D7C6",
    "height": 54,
    "width": 105,
    "x": 215,
    "y": 162
  },
  "hasClickThrough": false,
  "hasClippingMask": false,
  "isFlippedHorizontal": false,
  "isFlippedVertical": false,
  "isLocked": false,
  "isVisible": true,
  "layerListExpandedType": 0,
  "layers": [
    {
      "class": "rectangle",
      "id": "99D232D2-2EFB-4433-BD35-B3EC9AE9CCF5"
    }
  ],
  "name": "Shape",
  "nameIsFixed": false,
  "resizingConstraint": 63,
  "resizingType": 0,
  "rotation": 0,
  "shouldBreakMaskChain": false,
  "style": {
    "_class": "style",
    "borders": [
      {
        "_class": "border",
        "color": {
          "_class": "color",
          "alpha": 1,
          "blue": 0.592,
          "green": 0.592,
          "red": 0.592
        },
        "fillType": 0,
        "isEnabled": false,
        "position": 1,
        "thickness": 1
      }
    ],
    "do_objectID": "103FB283-800D-4F9C-A16E-BD8222BC56CA",
    "endDecorationType": 0,
    "fills": [
      {
        "_class": "fill",
        "color": {
          "_class": "color",
          "alpha": 1,
          "blue": 0.8313725490196079,
          "green": 0.7960784313725491,
          "red": 0.7764705882352941
        },
        "fillType": 0,
        "isEnabled": true,
        "noiseIndex": 0,
        "noiseIntensity": 0,
        "patternFillType": 0,
        "patternTileScale": 1
      }
    ],
    "miterLimit": 10,
    "startDecorationType": 0
  },
  "windingRule": 1
}