{
  "_class": "shapeGroup",
  "clippingMaskMode": 0,
  "do_objectID": "1CFB3DA7-0E04-4AAF-B4B0-F1E855DAA935",
  "exportOptions": {
    "_class": "exportOptions",
    "do_objectID": "1607785F-13AB-46E2-8624-4D9829115D18",
    "exportFormats": [
    ],
    "includedLayerIds": [
    ],
    "layerOptions": 0,
    "shouldTrim": false
  },
  "frame": {
    "_class": "rect",
    "constrainProportions": false,
    "do_objectID": "155B7D4C-084F-4744-98B2-AC2927DFF08A",
    "height": 29,
    "width": 29,
    "x": 0,
    "y": 0
  },
  "hasClickThrough": false,
  "hasClippingMask": false,
  "isFlippedHorizontal": false,
  "isFlippedVertical": false,
  "isLocked": false,
  "isVisible": true,
  "layerListExpandedType": 0,
  "layers": [
    {
      "class": "shapePath",
      "id": "9AA7D939-730B-4FAF-9BF5-3193EAB0FBAD"
    }
  ],
  "name": "Bounds",
  "nameIsFixed": true,
  "resizingConstraint": 63,
  "resizingType": 0,
  "rotation": 0,
  "shouldBreakMaskChain": false,
  "style": {
    "_class": "style",
    "do_objectID": "81A0B367-D982-46CC-8215-6BA6D8A51039",
    "endDecorationType": 0,
    "miterLimit": 10,
    "startDecorationType": 0
  },
  "windingRule": 1
}