{
  "_class": "shapeGroup",
  "clippingMaskMode": 0,
  "do_objectID": "A07151E3-374F-43D1-814A-F97B863F5ED9",
  "exportOptions": {
    "_class": "exportOptions",
    "do_objectID": "5AB31B27-3BC2-4808-8262-9ED2194BAE51",
    "exportFormats": [
    ],
    "includedLayerIds": [
    ],
    "layerOptions": 0,
    "shouldTrim": false
  },
  "frame": {
    "_class": "rect",
    "constrainProportions": false,
    "do_objectID": "124C68B9-CAD9-4FF8-8509-ECBF62BD9C47",
    "height": 29,
    "width": 29,
    "x": 0,
    "y": 0
  },
  "hasClickThrough": false,
  "hasClippingMask": false,
  "isFlippedHorizontal": false,
  "isFlippedVertical": false,
  "isLocked": false,
  "isVisible": true,
  "layerListExpandedType": 0,
  "layers": [
    {
      "class": "shapePath",
      "id": "FE533980-4C4C-47D2-A205-441276D156ED"
    }
  ],
  "name": "Bounds",
  "nameIsFixed": true,
  "resizingConstraint": 63,
  "resizingType": 0,
  "rotation": 0,
  "shouldBreakMaskChain": false,
  "style": {
    "_class": "style",
    "do_objectID": "7B84EA79-1CF8-4DB5-94CA-052E1F8E3C83",
    "endDecorationType": 0,
    "miterLimit": 10,
    "startDecorationType": 0
  },
  "windingRule": 1
}