{
  "_class": "shapeGroup",
  "clippingMaskMode": 0,
  "do_objectID": "5823463A-9140-486D-9897-2E44E8D44E4D",
  "exportOptions": {
    "_class": "exportOptions",
    "do_objectID": "48A90142-A432-4683-93A5-871BA0898E84",
    "exportFormats": [
    ],
    "includedLayerIds": [
    ],
    "layerOptions": 0,
    "shouldTrim": false
  },
  "frame": {
    "_class": "rect",
    "constrainProportions": false,
    "do_objectID": "96FC3269-29C9-43B0-8798-CD1BDDE92524",
    "height": 57,
    "width": 355.0000000000003,
    "x": 10,
    "y": 292
  },
  "hasClickThrough": false,
  "hasClippingMask": false,
  "isFlippedHorizontal": false,
  "isFlippedVertical": false,
  "isLocked": false,
  "isVisible": true,
  "layerListExpandedType": 0,
  "layers": [
    {
      "class": "rectangle",
      "id": "DEED1454-59B3-40A5-8468-6DEAE09D4885"
    }
  ],
  "name": "Button",
  "nameIsFixed": true,
  "resizingConstraint": 18,
  "resizingType": 2,
  "rotation": 0,
  "shouldBreakMaskChain": false,
  "style": {
    "_class": "style",
    "do_objectID": "C286F230-78CA-436C-AD7E-C53CE41ED585",
    "endDecorationType": 0,
    "fills": [
      {
        "_class": "fill",
        "color": {
          "_class": "color",
          "alpha": 1,
          "blue": 1,
          "green": 1,
          "red": 1
        },
        "fillType": 0,
        "isEnabled": true,
        "noiseIndex": 0,
        "noiseIntensity": 0,
        "patternFillType": 0,
        "patternTileScale": 1
      }
    ],
    "miterLimit": 10,
    "startDecorationType": 0
  },
  "windingRule": 1
}